odoo/addons/hr_employee_display_own_info/README.rst
odoo/addons/hr_employee_display_own_info/__init__.py
odoo/addons/hr_employee_display_own_info/__manifest__.py
odoo/addons/hr_employee_display_own_info/i18n/es.po
odoo/addons/hr_employee_display_own_info/i18n/hr_employee_display_own_info.pot
odoo/addons/hr_employee_display_own_info/models/__init__.py
odoo/addons/hr_employee_display_own_info/models/hr_employee.py
odoo/addons/hr_employee_display_own_info/readme/CONTRIBUTORS.rst
odoo/addons/hr_employee_display_own_info/readme/DESCRIPTION.rst
odoo/addons/hr_employee_display_own_info/static/description/icon.png
odoo/addons/hr_employee_display_own_info/static/description/index.html
odoo/addons/hr_employee_display_own_info/tests/__init__.py
odoo/addons/hr_employee_display_own_info/tests/test_employee_display_own_info.py
odoo/addons/hr_employee_display_own_info/views/hr_employee.xml
odoo11_addon_hr_employee_display_own_info-11.0.1.0.0.99.dev5.dist-info/METADATA
odoo11_addon_hr_employee_display_own_info-11.0.1.0.0.99.dev5.dist-info/WHEEL
odoo11_addon_hr_employee_display_own_info-11.0.1.0.0.99.dev5.dist-info/top_level.txt
odoo11_addon_hr_employee_display_own_info-11.0.1.0.0.99.dev5.dist-info/RECORD
